whitespace/__init__.py
whitespace/__main__.py
whitespace/cli.py
whitespace/error.py
whitespace/interpreter.py
whitespace/memory.py
whitespace/parser.py
whitespace/peripherals.py
whitespace/stack.py
whitespace/vm.py
whitespace/instructions/__init__.py
whitespace/instructions/arithmetic.py
whitespace/instructions/flow_control.py
whitespace/instructions/heap_access.py
whitespace/instructions/instruction.py
whitespace/instructions/io.py
whitespace/instructions/stack_manipulation.py
whitespace-1.0.0b8.dist-info/METADATA
whitespace-1.0.0b8.dist-info/RECORD
whitespace-1.0.0b8.dist-info/WHEEL
whitespace-1.0.0b8.dist-info/entry_points.txt
whitespace-1.0.0b8.dist-info/top_level.txt
