Metadata-Version: 1.1
Name: whitespace
Version: 1.0.0b8
Summary: A Whitespace interpreter.
Home-page: https://github.com/dwayne/whitespace-python
Author: Dwayne Crooks
Author-email: me@dwaynecrooks.com
License: MIT
Keywords: whitespace
Platform: UNKNOWN
Classifier: Development Status :: 4 - Beta
Classifier: Environment :: Console
Classifier: Intended Audience :: Developers
Classifier: License :: OSI Approved :: MIT License
Classifier: Operating System :: POSIX :: Linux
Classifier: Programming Language :: Python
Classifier: Programming Language :: Python :: Implementation :: CPython
Classifier: Topic :: Software Development :: Interpreters
